Sequential/Counters/counters.v

//Counters
`define TRUE 1'b1
`define FALSE 1'b0

module upcounter(Q,clk,clr);
input clk,clr;
output [3:0] Q;
reg Q;

always @(posedge clk) begin
    if(clr) Q=4'd0;
    else begin
        Q=(Q+1)%16;
    end
end
    
endmodule


//Ripple counter
// module counter (Q,clk,clr);
// input clk,clr;
// output [3:0] Q;

// tflipflop t0(clk,clr,Q[0]);
// tflipflop t1(Q[0],clr,Q[1]);
// tflipflop t2(Q[1],clr,Q[2]);
// tflipflop t3(Q[2],clr,Q[3]);

    
// endmodule

// module tflipflop (clk,clr,q);
// input clk,clr;
// output q;
// reg q;

// always @(posedge clk) begin
//     if (clr) q=0;
//     else
//         q=~q;

// end


//Up down counter
// module counter(clr,ld,mode,clk,d_in,out);
// input clr,ld,mode,clk;
// input [7:0] d_in;
// wire d_in;
// output [7:0] out;
// reg out;

// always @(posedge clk) begin
//     if(ld) out<=d_in;
//     else if (clr) out<=0;
//     else if (mode) out<=out+1;
//     else out<=out-1;
// end
    
// endmodule


//Parametrized Counter
// module counter (clk,clr,count);
// parameter N = 3;
// input clk,clr;
// output [0:N] count;
// reg count;

// always @(posedge clk) begin
//     if(clr) count<=0;
//     else count<=count+4'b 0001;
// end
    
// endmodule

Sequential/Counters/counters_tb.v
module test();
reg clk,clr;
wire [3:0] Q;

upcounter c(Q,clk,clr);

initial begin
    clk=`TRUE;
    forever #5 clk=~clk;
end

initial begin
    $dumpfile("counter.vcd");
    $dumpvars(0);
    clr=`FALSE;
    #10 clr=`TRUE;
    #200 clr=`FALSE;
end

// initial begin
//     t=1;
// end

initial begin
    $monitor($time," ","C[3]=%b C[2]=%b C[1]=%b C[0]=%b  Clear=%b",Q[3],Q[2],Q[1],Q[0],clr);
end

initial begin
    #400 $finish;
end

    
endmodule


// module test();
// reg clk,clr,ld,mode;
// reg [7:0] d_in;
// wire [7:0] out;

// counter c(clr,ld,mode,clk,d_in,out);

// initial begin
//     clk=`TRUE;
//     forever #5 clk=~clk;
// end

// initial begin
//     d_in=8'b 0;
// end

// initial begin
//     #10 clr=0;ld=1;mode=1;
//     #10 clr=0;ld=0;mode=1;
//     #10 clr=0;ld=1;mode=1;
// end

// initial begin
//     $monitor($time," ","out=%b",out);
//     #40 $finish;
// end

  
// endmodule



// module test ();
// reg clk,clr;
// parameter N = 3;
// wire [0:N] count;

// counter c(clk,clr,count);


// initial begin
//     clk=`TRUE;
//     forever #5 clk=~clk;
// end

// initial begin
//     #10 clr=0;
//     #10 clr=0;
//     #10 clr=1;
// end

// initial begin
//     $monitor($time," "," clr=%b, count=%b",clr,count);
//     #40 $finish;
// end

// endmodule

Sequential/Counters/counter.vcd
$date
	Sat Jun 03 00:59:10 2023
$end
$version
	Icarus Verilog
$end
$timescale
	1s
$end
$scope module test $end
$var wire 4 ! Q [3:0] $end
$var reg 1 " clk $end
$var reg 1 # clr $end
$scope module c $end
$var wire 1 $ clk $end
$var wire 1 % clr $end
$var reg 4 & Q [3:0] $end
$upscope $end
$upscope $end
$enddefinitions $end
#0
$dumpvars
bx &
0%
1$
0#
1"
bx !
$end
#5
0"
0$
#10
b0 &
b0 !
1"
1$
1#
1%
#15
0"
0$
#20
1"
1$
#25
0"
0$
#30
1"
1$
#35
0"
0$
#40
1"
1$
#45
0"
0$
#50
1"
1$
#55
0"
0$
#60
1"
1$
#65
0"
0$
#70
1"
1$
#75
0"
0$
#80
1"
1$
#85
0"
0$
#90
1"
1$
#95
0"
0$
#100
1"
1$
#105
0"
0$
#110
1"
1$
#115
0"
0$
#120
1"
1$
#125
0"
0$
#130
1"
1$
#135
0"
0$
#140
1"
1$
#145
0"
0$
#150
1"
1$
#155
0"
0$
#160
1"
1$
#165
0"
0$
#170
1"
1$
#175
0"
0$
#180
1"
1$
#185
0"
0$
#190
1"
1$
#195
0"
0$
#200
1"
1$
#205
0"
0$
#210
b1 &
b1 !
1"
1$
0#
0%
#215
0"
0$
#220
b10 &
b10 !
1"
1$
#225
0"
0$
#230
b11 &
b11 !
1"
1$
#235
0"
0$
#240
b100 &
b100 !
1"
1$
#245
0"
0$
#250
b101 &
b101 !
1"
1$
#255
0"
0$
#260
b110 &
b110 !
1"
1$
#265
0"
0$
#270
b111 &
b111 !
1"
1$
#275
0"
0$
#280
b1000 &
b1000 !
1"
1$
#285
0"
0$
#290
b1001 &
b1001 !
1"
1$
#295
0"
0$
#300
b1010 &
b1010 !
1"
1$
#305
0"
0$
#310
b1011 &
b1011 !
1"
1$
#315
0"
0$
#320
b1100 &
b1100 !
1"
1$
#325
0"
0$
#330
b1101 &
b1101 !
1"
1$
#335
0"
0$
#340
b1110 &
b1110 !
1"
1$
#345
0"
0$
#350
b1111 &
b1111 !
1"
1$
#355
0"
0$
#360
b0 &
b0 !
1"
1$
#365
0"
0$
#370
b1 &
b1 !
1"
1$
#375
0"
0$
#380
b10 &
b10 !
1"
1$
#385
0"
0$
#390
b11 &
b11 !
1"
1$
#395
0"
0$
#400
b100 &
b100 !
1"
1$
