FSM/Seq_det/seq.v
module seq_detector_1010(input clk, rst_n, x, output z);
  parameter A = 4'h1;
  parameter B = 4'h2;
  parameter C = 4'h3;
  parameter D = 4'h4;
  
  reg [3:0] state, next_state;
  always @(posedge clk or negedge rst_n) begin
    if(!rst_n) begin 
      state <= A;
    end
    else state <= next_state;
  end
  
  always @(state or x) begin
    case(state)
      A: begin
           if(x == 0) next_state = A;
           else       next_state = B;
         end
      B: begin
           if(x == 0) next_state = C;
           else       next_state = B;
         end
      C: begin
           if(x == 0) next_state = A;
           else       next_state = D;
         end
      D: begin
           if(x == 0) next_state = C;
           else       next_state = B;
         end
      default: next_state = A;
    endcase
  end
  assign z = (state == D)? 1:0;
endmodule

FSM/Seq_det/seq_tb.v
module TB;
  reg clk, rst_n, x;
  wire z;
  
  seq_detector_1010 sd(clk, rst_n, x, z);
  initial clk = 0;   
  always #2 clk = ~clk;
    
  initial begin
    $monitor("%0t: x = %0b, z = %0b", $time, x, z);
    x = 0;
    #1 rst_n = 0;
    #2 rst_n = 1;
    
    #3 x = 1;
    #4 x = 1;
    #4 x = 0;
    #4 x = 1;
    #4 x = 0;
    #4 x = 1;
    #4 x = 0;
    #4 x = 1;
    #4 x = 0;
    #4 x = 1;
    #4 x = 0;
    #10;
    $finish;
  end
  
  initial begin
    // Dump waves
    $dumpfile("dump.vcd");
    $dumpvars(0);
  end
endmodule

FSM/Seq_det/dump.vcd
$date
	Fri Apr 28 22:04:38 2023
$end
$version
	Icarus Verilog
$end
$timescale
	1s
$end
$scope module TB $end
$var wire 1 ! z $end
$var reg 1 " clk $end
$var reg 1 # rst_n $end
$var reg 1 $ x $end
$scope module sd $end
$var wire 1 % clk $end
$var wire 1 & rst_n $end
$var wire 1 ' x $end
$var wire 1 ! z $end
$var reg 4 ( next_state [3:0] $end
$var reg 4 ) state [3:0] $end
$upscope $end
$upscope $end
$enddefinitions $end
#0
$dumpvars
bx )
b1 (
0'
x&
0%
0$
x#
0"
x!
$end
#1
0!
b1 )
0#
0&
#2
1"
1%
#3
1#
1&
#4
0"
0%
#6
b10 )
b10 (
1"
1%
1$
1'
#8
0"
0%
#10
1"
1%
#12
0"
0%
#14
b11 )
b1 (
1"
1%
0$
0'
#16
0"
0%
#18
1!
b100 )
b10 (
1"
1%
1$
1'
#20
0"
0%
#22
0!
b11 )
b1 (
1"
1%
0$
0'
#24
0"
0%
#26
1!
b100 )
b10 (
1"
1%
1$
1'
#28
0"
0%
#30
0!
b11 )
b1 (
1"
1%
0$
0'
#32
0"
0%
#34
1!
b100 )
b10 (
1"
1%
1$
1'
#36
0"
0%
#38
0!
b11 )
b1 (
1"
1%
0$
0'
#40
0"
0%
#42
1!
b100 )
b10 (
1"
1%
1$
1'
#44
0"
0%
#46
0!
b11 )
b1 (
1"
1%
0$
0'
#48
0"
0%
#50
b1 )
1"
1%
