FSM/Seq_det/seq.v
//SEQUENCE DETECTOR 

//(a) 1010 (Mealey Machine Overlapping)
// module seq_1010(input din, clk, rst,
//                 output reg dout);
  

//   parameter S0 = 0, S1 = 1, S2 = 2, S3 = 3;
  
  
//   reg [2:0] state, next_state;
  
//   // Next State Logic - combinational logic to compute the next state based on the current state and input value
//   always @ (*) begin
//     case (state)
//       S0: next_state = din ? S1 : S0;
//       S1: next_state = din ? S1 : S2;
//       S2: next_state = din ? S3 : S0;
//       //S3: next_state = din ? S1 : S0;// This transition for non-overlaping sequence detector (If uncommented, comment the next line)
//       S3: next_state = din ? S1 : S2; // This transition for overlaping sequence detector (If uncommented, comment the previous line)
//       default: next_state = S0;
//     endcase
//   end
  
//   // State Memory - Assign the computed next state to the state memory on the clock edge
//   always @ (posedge clk) begin
//     if (rst) state <= 2'b00;
//     else state <= next_state;
//   end
  
//   // Output functional logic - The states for which the output should be '1'
//   always @ (posedge clk) begin
//     if (rst) dout <= 1'b0;
//     else begin
//       if (~din & (state == S3)) dout <= 1'b1;
//       else dout <= 1'b0;
//     end
//   end
// endmodule

//(b) 1101 (Mealey Machine Overlapping)
module seq_1101(input din, clk, rst,
                output reg dout);
  

  parameter S0 = 0, S1 = 1, S2 = 2, S3 = 3;
  
  
  reg [2:0] state, next_state;
  
  // Next State Logic - combinational logic to compute the next state based on the current state and input value
  always @ (*) begin
    case (state)
      S0: next_state = din ? S1 : S0;
      S1: next_state = din ? S2 : S0;
      S2: next_state = din ? S2 : S3;
      // S3: next_state = din ? S0 : S0;// This transition for non-overlaping sequence detector (If uncommented, comment the next line)
      S3: next_state = din ? S1 : S0; // This transition for overlaping sequence detector (If uncommented, comment the previous line)
      default: next_state = S0;
    endcase
  end
  
  // State Memory - Assign the computed next state to the state memory on the clock edge
  always @ (posedge clk) begin
    if (rst) state <= 2'b00;
    else state <= next_state;
  end
  
  // Output functional logic - The states for which the output should be '1'
  always @ (posedge clk) begin
    if (rst) dout <= 1'b0;
    else begin
      if (din & (state == S3)) dout <= 1'b1;
      else dout <= 1'b0;
    end
  end
endmodule
//(c)

FSM/Seq_det/seq_tb.v
module tb ();
  
  reg din, clk, rst;
  wire dout;
  wire [1:0] S;
  
  seq_1101 u0 (din, clk, rst, dout);
  
  always #1 clk = ~clk;
  
  initial begin
    clk = 0; rst = 1; din = 0;
    
    #5 rst = 0; din = 0;
    
    #1 din = 0;
    #2 din = 0;
    #2 din = 0;
    #2 din = 1;
    #2 din = 0;
    #2 din = 0;
    #2 din = 1;
    #2 din = 0;
    #2 din = 1;
    #2 din = 1;
    #2 din = 0;
    #2 din = 1;
    #2 din = 1;
    #2 din = 0;
    #2 din = 1;
    #2 din = 0;
    #40 $stop;
    
  end
  
  initial begin
  $dumpfile("dump.vcd");
    $dumpvars(0);
end
  
endmodule

FSM/Seq_det/dump.vcd
$date
	Sat Apr 29 12:44:03 2023
$end
$version
	Icarus Verilog
$end
$timescale
	1s
$end
$scope module tb $end
$var wire 1 ! dout $end
$var reg 1 " clk $end
$var reg 1 # din $end
$var reg 1 $ rst $end
$scope module u0 $end
$var wire 1 % clk $end
$var wire 1 & din $end
$var wire 1 ' rst $end
$var reg 1 ( dout $end
$var reg 3 ) next_state [2:0] $end
$var reg 3 * state [2:0] $end
$upscope $end
$upscope $end
$enddefinitions $end
#0
$dumpvars
bx *
b0 )
x(
1'
0&
0%
1$
0#
0"
x!
$end
#1
b0 *
0(
0!
1"
1%
#2
0"
0%
#3
1"
1%
#4
0"
0%
#5
1"
1%
0$
0'
#6
0"
0%
#7
1"
1%
#8
0"
0%
#9
1"
1%
#10
0"
0%
#11
1"
1%
#12
b1 )
0"
0%
1#
1&
#13
b10 )
b1 *
1"
1%
#14
b0 )
0"
0%
0#
0&
#15
b0 *
1"
1%
#16
0"
0%
#17
1"
1%
#18
b1 )
0"
0%
1#
1&
#19
b10 )
b1 *
1"
1%
#20
b0 )
0"
0%
0#
0&
#21
b0 *
1"
1%
#22
b1 )
0"
0%
1#
1&
#23
b10 )
b1 *
1"
1%
#24
0"
0%
#25
b10 *
1"
1%
#26
b11 )
0"
0%
0#
0&
#27
b0 )
b11 *
1"
1%
#28
0"
0%
1#
1&
#29
b1 )
b0 *
1(
1!
1"
1%
#30
0"
0%
#31
b10 )
0(
0!
b1 *
1"
1%
#32
b0 )
0"
0%
0#
0&
#33
b0 *
1"
1%
#34
b1 )
0"
0%
1#
1&
#35
b10 )
b1 *
1"
1%
#36
b0 )
0"
0%
0#
0&
#37
b0 *
1"
1%
